.project
.pydevproject
CHANGES.txt
MANIFEST.in
README.txt
setup.cfg
setup.py
docs/conf.py
docs/index.rst
tests/__init__.py
tests/test_widget.py
tw/__init__.py
tw.iphonecheck.egg-info/PKG-INFO
tw.iphonecheck.egg-info/SOURCES.txt
tw.iphonecheck.egg-info/dependency_links.txt
tw.iphonecheck.egg-info/entry_points.txt
tw.iphonecheck.egg-info/namespace_packages.txt
tw.iphonecheck.egg-info/not-zip-safe
tw.iphonecheck.egg-info/paster_plugins.txt
tw.iphonecheck.egg-info/requires.txt
tw.iphonecheck.egg-info/top_level.txt
tw/iphonecheck/__init__.py
tw/iphonecheck/release.py
tw/iphonecheck/samples.py
tw/iphonecheck/widgets.py
tw/iphonecheck/static/css/iphone-style-checkboxes.css
tw/iphonecheck/static/css/images/off.png
tw/iphonecheck/static/css/images/on.png
tw/iphonecheck/static/css/images/slider.png
tw/iphonecheck/static/css/images/slider_center.png
tw/iphonecheck/static/css/images/slider_left.png
tw/iphonecheck/static/css/images/slider_right.png
tw/iphonecheck/static/js/iphone-style-checkboxes.js