Metadata-Version: 1.0
Name: tw.iphonecheck
Version: 0.1
Summary: iphone like checkbox
Home-page: UNKNOWN
Author: Nicolas Laurance
Author-email: nicolas[dot]laurance[at]gmail[dot]com
License: UNKNOWN
Keywords: toscawidgets.widgets
Platform: UNKNOWN
Classifier: Development Status :: 3 - Alpha
Classifier: Environment :: Web Environment
Classifier: Environment :: Web Environment :: ToscaWidgets
Classifier: Topic :: Software Development :: Libraries :: Python Modules
Classifier: Topic :: Software Development :: Widget Sets
Classifier: Intended Audience :: Developers
Classifier: Operating System :: OS Independent
Classifier: Programming Language :: Python
Classifier: Framework :: TurboGears :: Widgets
Classifier: License :: OSI Approved :: MIT License
